brooal_mcp_demo/__init__.py
brooal_mcp_demo-0.1.0.dist-info/METADATA
brooal_mcp_demo-0.1.0.dist-info/WHEEL
brooal_mcp_demo-0.1.0.dist-info/entry_points.txt
brooal_mcp_demo-0.1.0.dist-info/RECORD
