Metadata-Version: 2.4
Name: brooal-mcp-demo
Version: 0.1.0
Summary: Add your description here
Author-email: "miniol_q@qq.com" <wjq13969512229@qq.com>
Requires-Python: >=3.13
Requires-Dist: mcp[cli]>=1.9.4
